{
  "base_language": "SC",
  "defaults": {
    "status": "translated"
  },
  "distribution_policy": {
    "contains_commercial_source_text": false,
    "contains_complete_game_resource": false
  },
  "entries": [
    {
      "block_id": 6,
      "ko": "\n권농",
      "literal_id": 1,
      "record_id": 1677,
      "source_sc_utf16le_sha256": "F3E6BA45D224906C5B1B0513237AABB965B317B459DD61D5C1A1B088CFF3B647"
    },
    {
      "block_id": 6,
      "ko": ", 상공",
      "literal_id": 2,
      "record_id": 1677,
      "source_sc_utf16le_sha256": "2DB903934044AB549437184E08A08DDCCC64A8A35B9C314F98246226EE7C0624"
    },
    {
      "block_id": 6,
      "ko": ", 기반 시설",
      "literal_id": 3,
      "record_id": 1677,
      "source_sc_utf16le_sha256": "E683EBBFA5423268069A0E38347F053D56321FC4D8F8E440FBF5BEDAD9AECA17"
    },
    {
      "block_id": 6,
      "ko": ", 문화",
      "literal_id": 4,
      "record_id": 1677,
      "source_sc_utf16le_sha256": "D45F48C5FFB472CE53C3A11614F09B234E3A308DC550A39DF8381BC2DC92E8D9"
    },
    {
      "block_id": 6,
      "ko": ", 치안",
      "literal_id": 5,
      "record_id": 1677,
      "source_sc_utf16le_sha256": "C47FFEB8008B4D178DA3EB0F0C4FECCB42830E6B646F06D87F8450F28824834E"
    },
    {
      "block_id": 6,
      "ko": "정책을 발령해 세력을 강화합니다.",
      "literal_id": 0,
      "record_id": 1680,
      "source_sc_utf16le_sha256": "4EFBCBF4DA021E4354B8F30DA16DEA48C3A204836F8CD267546CE5A056FF4F77"
    },
    {
      "block_id": 6,
      "ko": "정책 변경이 확정되지 않았습니다\n변경을 취소하시겠습니까?",
      "literal_id": 0,
      "record_id": 1681,
      "source_sc_utf16le_sha256": "659CB346160704804ACEE8F66C5A1CEA74F7056DEF3660D79DA22AC9EBABC956"
    },
    {
      "block_id": 6,
      "ko": "정책 변경을 확정합니다.",
      "literal_id": 0,
      "record_id": 1682,
      "source_sc_utf16le_sha256": "E9BEACBA322B67F82F76B06FF5EE89269D5427FE5E31456D6302C9791766119C"
    },
    {
      "block_id": 6,
      "ko": "변경된 항목이 없습니다",
      "literal_id": 0,
      "record_id": 1683,
      "source_sc_utf16le_sha256": "BEAA6C719FE06C9BE4273382182C6E6A1DF130B19BFD41E4964B2938786A5A6A"
    },
    {
      "block_id": 6,
      "ko": "조정을 의뢰한 세력과의 외교 자세가\n일시적으로 낮아지거나 오르지 않게 됩니다.\n계속하시겠습니까?",
      "literal_id": 0,
      "record_id": 1684,
      "source_sc_utf16le_sha256": "5BF56D194CBA5DEA339E8FA350BB02F624CC2BFF746F0C9CE89B4256A2B68AB2"
    },
    {
      "block_id": 6,
      "ko": "교섭 상대:",
      "literal_id": 0,
      "record_id": 1685,
      "source_sc_utf16le_sha256": "AB212F672EBBC6FA063EE0293D51053170741E4B0E0D14709DE6904A08F9CB89"
    },
    {
      "block_id": 6,
      "ko": ". 교섭이 성립하면\n다른 가문과 주고받던 원군이 중지됩니다.\n계속하시겠습니까?",
      "literal_id": 1,
      "record_id": 1685,
      "source_sc_utf16le_sha256": "7D3F8D6AB045CBDBE72120911E0163C6B65A3DDC2503B3E57CBE8FBF37F15303"
    },
    {
      "block_id": 6,
      "ko": "외교 관계를 파기할 상대:",
      "literal_id": 0,
      "record_id": 1686,
      "source_sc_utf16le_sha256": "5E0ECAC574D5A2BC1FA2B99AC7B25E019125772BC5F02151F317C27606954D12"
    },
    {
      "block_id": 6,
      "ko": ". 주변 세력의 불신을 사고\n가신의 충성도도 낮아질 수 있습니다.\n계속하시겠습니까?",
      "literal_id": 1,
      "record_id": 1686,
      "source_sc_utf16le_sha256": "AA525D37090EC54B79DD8A76B1CC1C3491247A7C6B66281C5AFEA1C5CDA51A32"
    },
    {
      "block_id": 6,
      "ko": "종속할 세력:",
      "literal_id": 0,
      "record_id": 1689,
      "source_sc_utf16le_sha256": "C85671CB51653DADD10A895C81145F8888BBA13364D707BC5DCFF25AC55CFB57"
    },
    {
      "block_id": 6,
      "ko": ". 종속하면\n다른 세력과의 외교 관계가 모두 해소됩니다.\n주의하십시오.",
      "literal_id": 1,
      "record_id": 1689,
      "source_sc_utf16le_sha256": "80AECF49ED25B61D08CCD3A1EB957743F237ABEACE0E8F4235A849D11BD8C8A2"
    },
    {
      "block_id": 6,
      "ko": "종속할 세력:",
      "literal_id": 0,
      "record_id": 1690,
      "source_sc_utf16le_sha256": "C85671CB51653DADD10A895C81145F8888BBA13364D707BC5DCFF25AC55CFB57"
    },
    {
      "block_id": 6,
      "ko": ". 종속하면\n다른 세력과의 외교 관계가 모두 해소됩니다.\n주의하십시오.",
      "literal_id": 1,
      "record_id": 1690,
      "source_sc_utf16le_sha256": "80AECF49ED25B61D08CCD3A1EB957743F237ABEACE0E8F4235A849D11BD8C8A2"
    },
    {
      "block_id": 6,
      "ko": "종속할 세력:",
      "literal_id": 0,
      "record_id": 1691,
      "source_sc_utf16le_sha256": "C85671CB51653DADD10A895C81145F8888BBA13364D707BC5DCFF25AC55CFB57"
    },
    {
      "block_id": 6,
      "ko": ". 종속하면\n다른 세력과의 외교 관계가 모두 해소됩니다.\n주의하십시오.",
      "literal_id": 1,
      "record_id": 1691,
      "source_sc_utf16le_sha256": "80AECF49ED25B61D08CCD3A1EB957743F237ABEACE0E8F4235A849D11BD8C8A2"
    },
    {
      "block_id": 6,
      "ko": "종속할 세력:",
      "literal_id": 0,
      "record_id": 1695,
      "source_sc_utf16le_sha256": "C85671CB51653DADD10A895C81145F8888BBA13364D707BC5DCFF25AC55CFB57"
    },
    {
      "block_id": 6,
      "ko": ". 종속하면\n다른 세력과의 외교 관계가 모두 해소됩니다.\n주의하십시오.",
      "literal_id": 1,
      "record_id": 1695,
      "source_sc_utf16le_sha256": "80AECF49ED25B61D08CCD3A1EB957743F237ABEACE0E8F4235A849D11BD8C8A2"
    },
    {
      "block_id": 6,
      "ko": "종속할 세력:",
      "literal_id": 0,
      "record_id": 1699,
      "source_sc_utf16le_sha256": "C85671CB51653DADD10A895C81145F8888BBA13364D707BC5DCFF25AC55CFB57"
    },
    {
      "block_id": 6,
      "ko": ". 종속하면\n다른 외교 관계가 모두 해소됩니다.\n계속하시겠습니까?",
      "literal_id": 1,
      "record_id": 1699,
      "source_sc_utf16le_sha256": "D882DFB7CCF56AC6FB4C1FC04EB98F1E85D9A6CB70DE442848E800674EB0035A"
    },
    {
      "block_id": 6,
      "ko": "칙명 강화를 사용하면\n다음 위계에 오를 때까지 다시 사용할 수 없습니다.\n주의하십시오.",
      "literal_id": 0,
      "record_id": 1702,
      "source_sc_utf16le_sha256": "80AD8737C0F5661E53E5296A237084D5B871E80F443A8EC5E0F89226D0E6D310"
    },
    {
      "block_id": 6,
      "ko": "칙명 강화를 사용하면\n다음 위계에 오를 때까지 다시 사용할 수 없습니다.\n주의하십시오.",
      "literal_id": 0,
      "record_id": 1703,
      "source_sc_utf16le_sha256": "80AD8737C0F5661E53E5296A237084D5B871E80F443A8EC5E0F89226D0E6D310"
    },
    {
      "block_id": 6,
      "ko": "칙명 강화를 사용하면\n다음 위계에 오를 때까지 다시 사용할 수 없습니다.\n주의하십시오.",
      "literal_id": 0,
      "record_id": 1704,
      "source_sc_utf16le_sha256": "80AD8737C0F5661E53E5296A237084D5B871E80F443A8EC5E0F89226D0E6D310"
    },
    {
      "block_id": 6,
      "ko": "칙명 강화를 사용하면\n다음 위계에 오를 때까지 다시 사용할 수 없습니다.\n주의하십시오.",
      "literal_id": 0,
      "record_id": 1708,
      "source_sc_utf16le_sha256": "80AD8737C0F5661E53E5296A237084D5B871E80F443A8EC5E0F89226D0E6D310"
    },
    {
      "block_id": 6,
      "ko": "일방적으로 단교하면 악명이 퍼져\n외교에 악영향을 줍니다.\n주의하십시오.",
      "literal_id": 0,
      "record_id": 1714,
      "source_sc_utf16le_sha256": "29E17B82B43F232FB50E55C095855E20B04912B8BF400C8396636A645668B961"
    },
    {
      "block_id": 6,
      "ko": "일방적으로 단교하면 악명이 퍼져\n외교에 악영향을 줍니다.\n주의하십시오.",
      "literal_id": 0,
      "record_id": 1715,
      "source_sc_utf16le_sha256": "29E17B82B43F232FB50E55C095855E20B04912B8BF400C8396636A645668B961"
    },
    {
      "block_id": 6,
      "ko": "일방적으로 단교하면 악명이 퍼져\n외교에 악영향을 줍니다.\n주의하십시오.",
      "literal_id": 0,
      "record_id": 1716,
      "source_sc_utf16le_sha256": "29E17B82B43F232FB50E55C095855E20B04912B8BF400C8396636A645668B961"
    },
    {
      "block_id": 6,
      "ko": "일방적으로 단교하면 악명이 퍼져\n외교에 악영향을 줍니다.\n주의하십시오.",
      "literal_id": 0,
      "record_id": 1720,
      "source_sc_utf16le_sha256": "29E17B82B43F232FB50E55C095855E20B04912B8BF400C8396636A645668B961"
    },
    {
      "block_id": 6,
      "ko": "본가 부대가 머무는 세력:",
      "literal_id": 0,
      "record_id": 1724,
      "source_sc_utf16le_sha256": "9286929BE9D05DD1398DED1B79B6C4EC8A82AB8118B2DC0215DF709F7E251FB2"
    },
    {
      "block_id": 6,
      "ko": ". 그 영내에서 단교하면\n악명이 크게 높아집니다.\n계속하시겠습니까?",
      "literal_id": 1,
      "record_id": 1724,
      "source_sc_utf16le_sha256": "076CDC2ED9887C60509848062C0E27D4E6D3290F74E5ACAEB26F1F570FC38E5E"
    },
    {
      "block_id": 6,
      "ko": "주가를 바꾸면 악명이 퍼져\n외교에 악영향을 줍니다.\n주의하십시오.",
      "literal_id": 0,
      "record_id": 1727,
      "source_sc_utf16le_sha256": "5BD9525A84783A2A807AC0ABB995B4B88D58BD3546F7C3E3AC0285C3AD4D9F6B"
    },
    {
      "block_id": 6,
      "ko": "주가를 바꾸면 악명이 퍼져\n외교에 악영향을 줍니다.\n주의하십시오.",
      "literal_id": 0,
      "record_id": 1728,
      "source_sc_utf16le_sha256": "5BD9525A84783A2A807AC0ABB995B4B88D58BD3546F7C3E3AC0285C3AD4D9F6B"
    },
    {
      "block_id": 6,
      "ko": "주가를 바꾸면 악명이 퍼져\n외교에 악영향을 줍니다.\n주의하십시오.",
      "literal_id": 0,
      "record_id": 1729,
      "source_sc_utf16le_sha256": "5BD9525A84783A2A807AC0ABB995B4B88D58BD3546F7C3E3AC0285C3AD4D9F6B"
    },
    {
      "block_id": 6,
      "ko": "주가를 바꾸면 악명이 퍼져\n외교에 악영향을 줍니다.\n주의하십시오.",
      "literal_id": 0,
      "record_id": 1733,
      "source_sc_utf16le_sha256": "5BD9525A84783A2A807AC0ABB995B4B88D58BD3546F7C3E3AC0285C3AD4D9F6B"
    },
    {
      "block_id": 6,
      "ko": "혼인할 무장이나 공주를 선택하십시오.",
      "literal_id": 0,
      "record_id": 1737,
      "source_sc_utf16le_sha256": "1BDA3937506A9F2E538164E63A2237275032E44405CBD22F11BD14ADC1032EF4"
    },
    {
      "block_id": 6,
      "ko": "혼인할 무장과 공주가 선택되지 않았습니다.",
      "literal_id": 0,
      "record_id": 1738,
      "source_sc_utf16le_sha256": "976EAC816905F8C901408412278DC6190501F6572DDCE81C654A202C35A57D86"
    },
    {
      "block_id": 6,
      "ko": "다음 세력과 단교시킬 상대:",
      "literal_id": 0,
      "record_id": 1739,
      "source_sc_utf16le_sha256": "5CBFD301D342E33133B4CAD3C03C800CAC42D01306EC45626EA766738F44943D"
    },
    {
      "block_id": 6,
      "ko": "\n선택하십시오.",
      "literal_id": 1,
      "record_id": 1739,
      "source_sc_utf16le_sha256": "E8A23FF6B67AB3110D0355BC18515C3927934A2BFB6E085C793B643C6A46D712"
    },
    {
      "block_id": 6,
      "ko": "이 세력과 단교할 상대:",
      "literal_id": 0,
      "record_id": 1740,
      "source_sc_utf16le_sha256": "92D914FEF0654D0C37482B6F532C72F8AB88ABE1E1FFB9E4FFFB679CCAF4C2D1"
    },
    {
      "block_id": 6,
      "ko": ".\n단교를 지시합니다.",
      "literal_id": 1,
      "record_id": 1740,
      "source_sc_utf16le_sha256": "2BCC71BC385E667086C872B02E776EA8C8D2F6D5A314C8A93C59B8ADEED9B87C"
    },
    {
      "block_id": 6,
      "ko": "다음 세력과 정전시킬 상대:",
      "literal_id": 0,
      "record_id": 1741,
      "source_sc_utf16le_sha256": "5CBFD301D342E33133B4CAD3C03C800CAC42D01306EC45626EA766738F44943D"
    },
    {
      "block_id": 6,
      "ko": "\n선택하십시오.",
      "literal_id": 1,
      "record_id": 1741,
      "source_sc_utf16le_sha256": "5F05A456370A5B3652534FC8683B64D036D5F9708DCD37683F8E995FEB284631"
    },
    {
      "block_id": 6,
      "ko": "이 세력과 정전할 상대:",
      "literal_id": 0,
      "record_id": 1742,
      "source_sc_utf16le_sha256": "92D914FEF0654D0C37482B6F532C72F8AB88ABE1E1FFB9E4FFFB679CCAF4C2D1"
    },
    {
      "block_id": 6,
      "ko": "\n정전을 지시합니다.",
      "literal_id": 1,
      "record_id": 1742,
      "source_sc_utf16le_sha256": "BE64B74D98FA0B2AF60F0DD471A881D0D883D6BF931698B2ECDC24CA58B4B68A"
    },
    {
      "block_id": 6,
      "ko": "다음 세력의 목표로 삼을 상대:",
      "literal_id": 0,
      "record_id": 1743,
      "source_sc_utf16le_sha256": "60B2FBE117DEFA34097F016ED6881D021C8B68B31851E220B0003E64731E8640"
    },
    {
      "block_id": 6,
      "ko": "\n선택하십시오.",
      "literal_id": 1,
      "record_id": 1743,
      "source_sc_utf16le_sha256": "7BF507454149E266C5551B88C6DCFDE782EB48460E738F04FAF7BDD2CB1B803C"
    },
    {
      "block_id": 6,
      "ko": "이 세력을 다음 세력의 목표로 지정합니다:",
      "literal_id": 0,
      "record_id": 1744,
      "source_sc_utf16le_sha256": "4DB447A981E6368719F7B72C870B679DBFECADFCC4B5FFECA980815081DF4F06"
    },
    {
      "block_id": 6,
      "ko": ".",
      "literal_id": 1,
      "record_id": 1744,
      "source_sc_utf16le_sha256": "E4E6FDC0CE9C61EB9572F1F68A7B54BBD3BE19CE7F0AEDD2787163927626DB0C"
    },
    {
      "block_id": 6,
      "ko": "원군을 보낼 목표 성을 선택하십시오.",
      "literal_id": 0,
      "record_id": 1745,
      "source_sc_utf16le_sha256": "C498C02262B89C595F3C56DFB54C0DDCB7A4D552AE2D9CAA7ABEFC6643F2186B"
    },
    {
      "block_id": 6,
      "ko": "이 세력을 원군 목표로 지정할 세력:\n",
      "literal_id": 0,
      "record_id": 1746,
      "source_sc_utf16le_sha256": "882E2848AC9D11D28FAE7D28DAA11EA24A7EB780E187B4659807BC138A1C9ECD"
    },
    {
      "block_id": 6,
      "ko": "입니다.",
      "literal_id": 1,
      "record_id": 1746,
      "source_sc_utf16le_sha256": "DB11301D7033C387E56A1D7F04B8F582DCE66990639A21A3A382DEECCECB4DA6"
    },
    {
      "block_id": 6,
      "ko": "제안할 가보를 선택하십시오.",
      "literal_id": 0,
      "record_id": 1747,
      "source_sc_utf16le_sha256": "73ADD1A4B7A4AF3825A680545738606781571F0CD56014337B68CF7787DF74A5"
    },
    {
      "block_id": 6,
      "ko": "제안할 관직을 선택하십시오.",
      "literal_id": 0,
      "record_id": 1748,
      "source_sc_utf16le_sha256": "27F75816888043B05D46591DCD17EE6A2024B429447ECE2F344039472FD990E5"
    },
    {
      "block_id": 6,
      "ko": "단교할 세력을 선택하십시오.",
      "literal_id": 0,
      "record_id": 1749,
      "source_sc_utf16le_sha256": "1B867304D2F25131D3BAC036D30E892DFEB12AAE57F0489EF32A6F446A9BCB78"
    },
    {
      "block_id": 6,
      "ko": "교섭의 대가로 이 세력과 단교합니다.",
      "literal_id": 0,
      "record_id": 1750,
      "source_sc_utf16le_sha256": "3572734A3676B52B1306E3A28CA6609BDE916FF35730D70E6B824EEC086E9AA8"
    },
    {
      "block_id": 6,
      "ko": "군이나 성을 교환하면\n자동으로 6개월 정전이 맺어집니다.\n계속하시겠습니까?",
      "literal_id": 0,
      "record_id": 1751,
      "source_sc_utf16le_sha256": "D477B3524D705F56052BF4B45C96992DC1EF7E80D2C4FEFC78022F35B93EA684"
    },
    {
      "block_id": 6,
      "ko": "원군이나 조정 교섭에 필요한 신용입니다.",
      "literal_id": 0,
      "record_id": 1752,
      "source_sc_utf16le_sha256": "FCC78C43060393482DC5B09C54E6CC4836A835A5A3C572AB5589D6A255FE9AD3"
    },
    {
      "block_id": 6,
      "ko": "동맹 교섭에 필요한 신용입니다.",
      "literal_id": 0,
      "record_id": 1753,
      "source_sc_utf16le_sha256": "92BE5A97399DCA8DD926B08B9B85266F938C91180A124E870491FDC593BD2231"
    },
    {
      "block_id": 6,
      "ko": "혼인 동맹 교섭에 필요한 신용입니다.",
      "literal_id": 0,
      "record_id": 1754,
      "source_sc_utf16le_sha256": "B8C737C70F189201D87EB1AD64DDE97C63E377BC041349664ACB9F9F98858D41"
    },
    {
      "block_id": 6,
      "ko": "혼인 동맹이나 직위 교섭에 필요한 신용입니다.",
      "literal_id": 0,
      "record_id": 1755,
      "source_sc_utf16le_sha256": "00C3BE24666B0C18C31D21CCC505AF06007AB02B61F3D116498C0646680784B8"
    },
    {
      "block_id": 6,
      "ko": "동맹이나 종속 관계가 아니면 원군이나 조정을 의뢰할 수 없습니다.",
      "literal_id": 0,
      "record_id": 1756,
      "source_sc_utf16le_sha256": "D6DD40240F118B3CB8F4E0E7E4D15D2EAD75DD4CB7BA021B3B4E4A5F9AAE250F"
    },
    {
      "block_id": 6,
      "ko": "동맹 관계가 아니면 혼인 동맹을 신청할 수 없습니다.",
      "literal_id": 0,
      "record_id": 1757,
      "source_sc_utf16le_sha256": "CCD52B99317A8C4A2AF6D5419E03361F31A8EE83DA57F30DD7A1DBBB19A132FD"
    },
    {
      "block_id": 6,
      "ko": "쇼군 가문 이외의 먼 세력과는 외교할 수 없습니다.",
      "literal_id": 0,
      "record_id": 1758,
      "source_sc_utf16le_sha256": "DCEB21B1208DC500A0AEA012C3709268343A971673D17B9E10492B06A1BC43E7"
    },
    {
      "block_id": 6,
      "ko": "본가가 다른 가문에 종속되어 있어 주군 세력 이외와 외교할 수 없습니다.",
      "literal_id": 0,
      "record_id": 1759,
      "source_sc_utf16le_sha256": "59D913C9BD25D7234AF41C7FCC208AD3537D6E7C415F9E98B719DB9E16934117"
    },
    {
      "block_id": 6,
      "ko": "상대가 다른 세력에 종속되어 있어 외교할 수 없습니다.",
      "literal_id": 0,
      "record_id": 1760,
      "source_sc_utf16le_sha256": "94B3075E7D92E6514EB71794FA4056EFA01569D777C523A899C42B8E84CD384D"
    },
    {
      "block_id": 6,
      "ko": "상대가 본가의 친선을 거부하고 있습니다.",
      "literal_id": 0,
      "record_id": 1761,
      "source_sc_utf16le_sha256": "0F50D97ABE0330FE0C15F353FA2397800B6799854D90CF20251E111F89B2D1CD"
    },
    {
      "block_id": 6,
      "ko": "친선에 필요한 금전이 부족합니다.",
      "literal_id": 0,
      "record_id": 1762,
      "source_sc_utf16le_sha256": "479838A34D4E348220CC0A4084A7F6CA8F26CCB1D42A9949ADE58B980602B6F4"
    },
    {
      "block_id": 6,
      "ko": "중개자가 될 수 있는 무장이 없습니다.",
      "literal_id": 0,
      "record_id": 1763,
      "source_sc_utf16le_sha256": "CC6F6EBB08CC9F36D3C83CBF88812986FD3C85B14773C3503487E1D3D242D43F"
    },
    {
      "block_id": 6,
      "ko": "본가가 다른 가문에 종속되어 있어 주군 세력 이외와 외교할 수 없습니다.",
      "literal_id": 0,
      "record_id": 1764,
      "source_sc_utf16le_sha256": "59D913C9BD25D7234AF41C7FCC208AD3537D6E7C415F9E98B719DB9E16934117"
    },
    {
      "block_id": 6,
      "ko": "상대가 다른 세력에 종속되어 있어 외교할 수 없습니다.",
      "literal_id": 0,
      "record_id": 1765,
      "source_sc_utf16le_sha256": "94B3075E7D92E6514EB71794FA4056EFA01569D777C523A899C42B8E84CD384D"
    },
    {
      "block_id": 6,
      "ko": "상대는 본가와 교섭할 뜻이 없습니다.",
      "literal_id": 0,
      "record_id": 1766,
      "source_sc_utf16le_sha256": "6CE56EF51C5D509AFA41F42DDBA6D3511FFAFD16FD8EA5A7C0DE72C7DB1EA989"
    },
    {
      "block_id": 6,
      "ko": "교섭할 수 있는 항목이 없습니다.",
      "literal_id": 0,
      "record_id": 1767,
      "source_sc_utf16le_sha256": "1E05B771A8495E338B2F4AD171C062165E3B052DF24310F3A019BFD4EEA79978"
    },
    {
      "block_id": 6,
      "ko": "막부 세력에는 직위를 줄 수 없습니다.",
      "literal_id": 0,
      "record_id": 1768,
      "source_sc_utf16le_sha256": "964A8B6E3FBC1F9B053BB52037DA8D9A5BBA870B9A0294BA75F71656699F5C02"
    },
    {
      "block_id": 6,
      "ko": "다른 가문에 종속된 세력에는 직위를 줄 수 없습니다.",
      "literal_id": 0,
      "record_id": 1769,
      "source_sc_utf16le_sha256": "D9572836D0045BC56ECFC1F04BD047E695103C368058F9CE9B332ECE9AB581E6"
    },
    {
      "block_id": 6,
      "ko": "상대가 본가와의 교섭을 거부하고 있습니다.",
      "literal_id": 0,
      "record_id": 1770,
      "source_sc_utf16le_sha256": "E87F46318AD9B807DB3A5BADD607AB01B559F3E8F548A153F1F0912E9C120EDF"
    },
    {
      "block_id": 6,
      "ko": "외교 자세를 더 개선할 수 없습니다.",
      "literal_id": 0,
      "record_id": 1771,
      "source_sc_utf16le_sha256": "73E592885F585C6EA824855026BF0F1636A25B2A82617DCABD55ED5EB9F1134A"
    },
    {
      "block_id": 6,
      "ko": "이 세력에 줄 수 있는 직위가 없습니다.",
      "literal_id": 0,
      "record_id": 1772,
      "source_sc_utf16le_sha256": "DF14021FC44F230BBEF2BA4D02A908DC902F1229F5CF13C49327F6E9186171A0"
    },
    {
      "block_id": 6,
      "ko": "교전 중이거나 교전을 마친 지 얼마 되지 않았습니다.",
      "literal_id": 0,
      "record_id": 1773,
      "source_sc_utf16le_sha256": "DF9B6D24CD1161D78727C19B2F632E38A4C1EDB850DD804D87D2EC0770819848"
    },
    {
      "block_id": 6,
      "ko": "공물의 효과가 앞으로",
      "literal_id": 0,
      "record_id": 1774,
      "source_sc_utf16le_sha256": "746DD610349325CC714EC004D56A9FE0DEF0492CE7E7665681A4E828BB632392"
    },
    {
      "block_id": 6,
      "ko": "개월간 지속됩니다.",
      "literal_id": 1,
      "record_id": 1774,
      "source_sc_utf16le_sha256": "F5724FAFF8A44236862A8FE1131AE5970667E61D8EFC4CBCD8E6708BEDD71726"
    },
    {
      "block_id": 6,
      "ko": "동맹 기간:",
      "literal_id": 0,
      "record_id": 1775,
      "source_sc_utf16le_sha256": "2C1E963F92C7DFD0C4E8E5614A7E3CB59B020597EBF20BE088A862B8776EA45E"
    },
    {
      "block_id": 6,
      "ko": "개월을 제안합니다.",
      "literal_id": 1,
      "record_id": 1775,
      "source_sc_utf16le_sha256": "2C185D8D1EF0300AA19BC32D9CC4DCDB0ED5A7FC62AEAA56A0E3B1858BB7325F"
    },
    {
      "block_id": 6,
      "ko": "성 공략을 위한 원군을 요청합니다.",
      "literal_id": 0,
      "record_id": 1776,
      "source_sc_utf16le_sha256": "12AF926B23861E6536F807569BF8B24283E8C57A0647E2173204D79A2EB23ECA"
    },
    {
      "block_id": 6,
      "ko": "지정 세력과의 정전 기간:",
      "literal_id": 0,
      "record_id": 1777,
      "source_sc_utf16le_sha256": "E4C75A9C93371AF4502DB899A3AA50A3C133E1703BBD21C1BA2EF5A37F98588A"
    },
    {
      "block_id": 6,
      "ko": "개월의 조정을 의뢰합니다.",
      "literal_id": 1,
      "record_id": 1777,
      "source_sc_utf16le_sha256": "E1050CD11FF9423A389E256931DD2A442B9684D1B02CF5A5728DB2C1D439F936"
    },
    {
      "block_id": 6,
      "ko": "혼인 동맹 체결을 제안합니다.",
      "literal_id": 0,
      "record_id": 1778,
      "source_sc_utf16le_sha256": "519028A68EF803FE4F61311E0A931918A49D7C9DDD6565925618248777C8DB80"
    },
    {
      "block_id": 6,
      "ko": "외교 관계를 파기합니다.",
      "literal_id": 0,
      "record_id": 1779,
      "source_sc_utf16le_sha256": "499BE5C03865011AE6F3EE598696910D8B50E0323963536858C0129354A50FE8"
    },
    {
      "block_id": 6,
      "ko": "본가에 종속하도록 권고합니다.",
      "literal_id": 0,
      "record_id": 1780,
      "source_sc_utf16le_sha256": "E775D84EB86479F06291EC94EE9B36DEF8431D5A61A099091D79C62D13171239"
    },
    {
      "block_id": 6,
      "ko": "상대에게 신종을 요청합니다.",
      "literal_id": 0,
      "record_id": 1781,
      "source_sc_utf16le_sha256": "A96D372094027FF4CA6C9BE9AE9C427E5ABF5E26047D93A1865F62A350DF24CE"
    },
    {
      "block_id": 6,
      "ko": "막부에 직위 수여를 요청합니다.",
      "literal_id": 0,
      "record_id": 1782,
      "source_sc_utf16le_sha256": "F44A808F3F430BB1A93550B9D2D537FA81166957E16874DA1E320660D1E8238F"
    },
    {
      "block_id": 6,
      "ko": "본가 또는 종속 세력의 성 방어를 요청합니다.",
      "literal_id": 0,
      "record_id": 1783,
      "source_sc_utf16le_sha256": "8F143CC55CD68EEC12ED40BE88F81EB3D46BA6F03A3D3A30F92A3D9F9C76F64C"
    },
    {
      "block_id": 6,
      "ko": "어느 세력도 본가와 친선할 뜻이 없습니다.",
      "literal_id": 0,
      "record_id": 1784,
      "source_sc_utf16le_sha256": "0BA71178CC4CDF27E114868FD2C72E95433EFA1738E9712E3E4D5FB89FF07CCE"
    },
    {
      "block_id": 6,
      "ko": "친선에 필요한 금전이 부족합니다.",
      "literal_id": 0,
      "record_id": 1785,
      "source_sc_utf16le_sha256": "479838A34D4E348220CC0A4084A7F6CA8F26CCB1D42A9949ADE58B980602B6F4"
    },
    {
      "block_id": 6,
      "ko": "중개자가 될 수 있는 무장이 없습니다.",
      "literal_id": 0,
      "record_id": 1786,
      "source_sc_utf16le_sha256": "CC6F6EBB08CC9F36D3C83CBF88812986FD3C85B14773C3503487E1D3D242D43F"
    },
    {
      "block_id": 6,
      "ko": "어느 세력도 본가와 교섭할 뜻이 없습니다.",
      "literal_id": 0,
      "record_id": 1787,
      "source_sc_utf16le_sha256": "C679112DEE1931EB99F7FA20E9CBEB4D949C9954DB8C326869E9E35830AA4179"
    },
    {
      "block_id": 6,
      "ko": "어느 세력과도 교섭할 수 있는 항목이 없습니다",
      "literal_id": 0,
      "record_id": 1788,
      "source_sc_utf16le_sha256": "952362AF61393B106D2AE2FD76D6462DF90199D13723FE48CF959287E3CE07EE"
    },
    {
      "block_id": 6,
      "ko": "이미 장기 동맹을 맺고 있습니다.",
      "literal_id": 0,
      "record_id": 1789,
      "source_sc_utf16le_sha256": "2367FE078520BF067C214B073DD042BA22808544C6F6E8092DA34BB0B75EFC1C"
    },
    {
      "block_id": 6,
      "ko": "본가가 종속되어 있어 동맹을 맺을 수 없습니다.",
      "literal_id": 0,
      "record_id": 1790,
      "source_sc_utf16le_sha256": "FF509306B2E6AC681477A2D2BC22E6A8AA45B65514892BE1D7279BEAA7D7BB81"
    },
    {
      "block_id": 6,
      "ko": "상대가 종속되어 있어 동맹을 맺을 수 없습니다.",
      "literal_id": 0,
      "record_id": 1791,
      "source_sc_utf16le_sha256": "129BD55AA7E5ADB946BEFD26A5131B8658EA8B947E80C375F9CCCA466A0BE7BD"
    },
    {
      "block_id": 6,
      "ko": "상대가 본가와의 교섭을 거부하고 있습니다.",
      "literal_id": 0,
      "record_id": 1792,
      "source_sc_utf16le_sha256": "E87F46318AD9B807DB3A5BADD607AB01B559F3E8F548A153F1F0912E9C120EDF"
    },
    {
      "block_id": 6,
      "ko": "신용이 부족합니다.",
      "literal_id": 0,
      "record_id": 1793,
      "source_sc_utf16le_sha256": "45E3C548EEC38EDF74231A8E53D9186838CEFAEE27092366A61CF68AC0AF3417"
    },
    {
      "block_id": 6,
      "ko": "교전 중이거나 교전 직후인 세력과는 동맹을 맺을 수 없습니다.",
      "literal_id": 0,
      "record_id": 1794,
      "source_sc_utf16le_sha256": "732A7A4D7E859AD26413BA19D4C5A3C3D47C97FEA45FAD30A1198A6D2EC0DAA7"
    },
    {
      "block_id": 6,
      "ko": "다른 가문이 요청한 원군이 상대와 교전 중입니다",
      "literal_id": 0,
      "record_id": 1795,
      "source_sc_utf16le_sha256": "5E95DA9AA63161AEBAAC1D1B7ECBF9C5EB9D8AD171C23DBBBCB856F34A0B8A1D"
    },
    {
      "block_id": 6,
      "ko": "신종한 세력 이외에는 원군을 요청할 수 없습니다.",
      "literal_id": 0,
      "record_id": 1796,
      "source_sc_utf16le_sha256": "965C86F0B6834AF8FC0478C1832159C5B33F501337B0DF28D1C90DC7E1E18CEA"
    },
    {
      "block_id": 6,
      "ko": "상대가 본가 이외의 세력에 신종하여 원군을 요청할 수 없습니다.",
      "literal_id": 0,
      "record_id": 1797,
      "source_sc_utf16le_sha256": "6FF712AB459B65548697E0B692D294E2B443D5B5DF78BF2B870D06CC23E51B82"
    },
    {
      "block_id": 6,
      "ko": "동맹 또는 종속 관계가 아니면 원군을 요청할 수 없습니다.",
      "literal_id": 0,
      "record_id": 1798,
      "source_sc_utf16le_sha256": "620132B0C3BF188FD168E9D019D20340E1B0625EAC9E24AF6002DAAF003428F2"
    },
    {
      "block_id": 6,
      "ko": "이미 상대에게 원군을 요청했습니다.",
      "literal_id": 0,
      "record_id": 1799,
      "source_sc_utf16le_sha256": "7BBB73541B5C8DDC36B4A2BE48F77531166A6317C347341EDB7EC296BEDEB958"
    },
    {
      "block_id": 6,
      "ko": "원군을 의뢰할 수 있는 성이 없습니다.",
      "literal_id": 0,
      "record_id": 1800,
      "source_sc_utf16le_sha256": "96E120FF02D66EECF52108BA873FC7C3B8DAECB95D62C80216B862B10D99C086"
    },
    {
      "block_id": 6,
      "ko": "상대는 현재 원군을 보낼 수 없는 상태입니다.",
      "literal_id": 0,
      "record_id": 1801,
      "source_sc_utf16le_sha256": "D11B77DCDDE0994D0338840EA423D37A50D4F9B84B11330A918160EB837B9FD3"
    },
    {
      "block_id": 6,
      "ko": "상대가 본가와의 교섭을 거부하고 있습니다.",
      "literal_id": 0,
      "record_id": 1802,
      "source_sc_utf16le_sha256": "E87F46318AD9B807DB3A5BADD607AB01B559F3E8F548A153F1F0912E9C120EDF"
    },
    {
      "block_id": 6,
      "ko": "신용이 부족합니다.",
      "literal_id": 0,
      "record_id": 1803,
      "source_sc_utf16le_sha256": "45E3C548EEC38EDF74231A8E53D9186838CEFAEE27092366A61CF68AC0AF3417"
    },
    {
      "block_id": 6,
      "ko": "신종한 세력 이외에는 조정을 의뢰할 수 없습니다.",
      "literal_id": 0,
      "record_id": 1804,
      "source_sc_utf16le_sha256": "395A9DF4FECB1DDECD365E9AC2C5FBBC28C6E488CB3C50B114F32C5E4DC1BB71"
    },
    {
      "block_id": 6,
      "ko": "상대가 종속 세력이므로 조정을 의뢰할 수 없습니다.",
      "literal_id": 0,
      "record_id": 1805,
      "source_sc_utf16le_sha256": "13ADF7EBADFFC2A62404414CC6BC4D45B1FC2A91CB31710F2B7B93B0A10DBCED"
    },
    {
      "block_id": 6,
      "ko": "동맹 또는 종속 관계가 아니면 조정을 의뢰할 수 없습니다.",
      "literal_id": 0,
      "record_id": 1806,
      "source_sc_utf16le_sha256": "FEA040B0B378EAAFE3289C293FBA31AFF4F3C982CAD0251AAFC4D57630E5C3B6"
    },
    {
      "block_id": 6,
      "ko": "상대가 정전을 조정할 수 있는 세력이 없습니다.",
      "literal_id": 0,
      "record_id": 1807,
      "source_sc_utf16le_sha256": "55B1EDB9C2E9A44D49FF4CEA42E076F75E1D9C0AE7D3059B5EB45CA85E4D0C43"
    },
    {
      "block_id": 6,
      "ko": "상대가 본가와의 교섭을 거부하고 있습니다.",
      "literal_id": 0,
      "record_id": 1808,
      "source_sc_utf16le_sha256": "E87F46318AD9B807DB3A5BADD607AB01B559F3E8F548A153F1F0912E9C120EDF"
    },
    {
      "block_id": 6,
      "ko": "신용이 부족합니다.",
      "literal_id": 0,
      "record_id": 1809,
      "source_sc_utf16le_sha256": "45E3C548EEC38EDF74231A8E53D9186838CEFAEE27092366A61CF68AC0AF3417"
    },
    {
      "block_id": 6,
      "ko": "이미 혼인 관계를 맺고 있습니다.",
      "literal_id": 0,
      "record_id": 1810,
      "source_sc_utf16le_sha256": "47A1418FBFC412A8E9C87F983B2E391031DB644946FFABE09D6CD25F58A14419"
    },
    {
      "block_id": 6,
      "ko": "본가가 종속되어 있어 혼인 동맹을 맺을 수 없습니다.",
      "literal_id": 0,
      "record_id": 1811,
      "source_sc_utf16le_sha256": "883AEF4647054B1203F2F89B3B4FC608FA7528EAD331E0FDDDD1F2AD9A24AA4A"
    },
    {
      "block_id": 6,
      "ko": "동맹 관계가 아니면 혼인 동맹을 맺을 수 없습니다.",
      "literal_id": 0,
      "record_id": 1812,
      "source_sc_utf16le_sha256": "5BA70ED8B5CC398ABBE565D7F9B8AB1F01319D6581B51B65C441489C84DAE54E"
    },
    {
      "block_id": 6,
      "ko": "상대가 종속되어 있어 혼인 동맹을 맺을 수 없습니다.",
      "literal_id": 0,
      "record_id": 1813,
      "source_sc_utf16le_sha256": "B57516A38B3363C9404B853E2734C0FE0B065671976358EB7D436D78306B5E60"
    },
    {
      "block_id": 6,
      "ko": "혼인할 수 있는 공주나 무장이 없습니다.",
      "literal_id": 0,
      "record_id": 1814,
      "source_sc_utf16le_sha256": "CF180A1B80B31F8503E1F797E0277D838DF4BF88776DF30582BBA711A383221F"
    },
    {
      "block_id": 6,
      "ko": "상대가 본가와의 교섭을 거부하고 있습니다.",
      "literal_id": 0,
      "record_id": 1815,
      "source_sc_utf16le_sha256": "E87F46318AD9B807DB3A5BADD607AB01B559F3E8F548A153F1F0912E9C120EDF"
    },
    {
      "block_id": 6,
      "ko": "신용이 부족합니다.",
      "literal_id": 0,
      "record_id": 1816,
      "source_sc_utf16le_sha256": "45E3C548EEC38EDF74231A8E53D9186838CEFAEE27092366A61CF68AC0AF3417"
    },
    {
      "block_id": 6,
      "ko": "상대와 끊을 수 있는 외교 관계가 없습니다.",
      "literal_id": 0,
      "record_id": 1817,
      "source_sc_utf16le_sha256": "1D4CBB7FACCE3F88AEC88CABBDC8751B681136C7515791D4E836F6AF1D27F0B0"
    },
    {
      "block_id": 6,
      "ko": "원군 요청 기간 중이므로 파기할 수 없습니다.",
      "literal_id": 0,
      "record_id": 1818,
      "source_sc_utf16le_sha256": "E80B3863743383319764BBC96CA1C689F0312E46DF649F77F44EA7B826ECFA72"
    },
    {
      "block_id": 6,
      "ko": "본가 부대가 상대 또는 상대의 종속 세력 영내에\n있거나 진입하려 하고 있습니다.",
      "literal_id": 0,
      "record_id": 1819,
      "source_sc_utf16le_sha256": "0E9CD8CC23FE33F4EAE3310F611350248A45F93F29B16317A0BDAA9FD897DB7A"
    },
    {
      "block_id": 6,
      "ko": "막부는 다른 가문의 휘하에 들어갈 수 없습니다.",
      "literal_id": 0,
      "record_id": 1820,
      "source_sc_utf16le_sha256": "1F2EBF1E5CE85CCAEABFE2A569A3BD6009458A599D25DDB58A0A570E1C8FDA91"
    },
    {
      "block_id": 6,
      "ko": "이미 상대와 주종 관계입니다.",
      "literal_id": 0,
      "record_id": 1821,
      "source_sc_utf16le_sha256": "00E7F1C46D271B93885F3C3C506DCFEC1E3AE70CF9729A6A7E1074CE58938A21"
    },
    {
      "block_id": 6,
      "ko": "본가가 독립 상태가 아니므로 다른 가문을 종속시킬 수 없습니다.",
      "literal_id": 0,
      "record_id": 1822,
      "source_sc_utf16le_sha256": "23F1230FCE805EBD14DF413429556ED44F0A023825C1F51B39D936F34B9A92A3"
    },
    {
      "block_id": 6,
      "ko": "다른 가문과 동맹·종속·신종 관계인 세력은\n종속시킬 수 없습니다.",
      "literal_id": 0,
      "record_id": 1823,
      "source_sc_utf16le_sha256": "707CD79C62DD234B461BF5D105B45C2D821973042511DBBC978422081C0BF3D0"
    },
    {
      "block_id": 6,
      "ko": "너무 멀어 종속시킬 수 없습니다.",
      "literal_id": 0,
      "record_id": 1824,
      "source_sc_utf16le_sha256": "4385CF81CC038F0DEA5A9A688EF6BEB344DEFD16539F644722FAA9842C85C734"
    },
    {
      "block_id": 6,
      "ko": "본가 또는 종속 세력과 인접하지 않습니다.",
      "literal_id": 0,
      "record_id": 1825,
      "source_sc_utf16le_sha256": "AA319B119900B4AF47B2404B37B651FC89D4BAF7C39B7B432CAC0669EEEAC851"
    },
    {
      "block_id": 6,
      "ko": "상대가 본가에 종속되기를 거부하고 있습니다.",
      "literal_id": 0,
      "record_id": 1826,
      "source_sc_utf16le_sha256": "D47B092F8517C14CB2A70254AF007F3C6F8DA1B35BC717B7200744CA11D492C1"
    },
    {
      "block_id": 6,
      "ko": "상대가 아직 강대하여 종속시킬 수 없습니다.",
      "literal_id": 0,
      "record_id": 1827,
      "source_sc_utf16le_sha256": "D4FB9C4014FEF511E3315D3DC09CB4B363665DDCB1C8A24F3149E6BE0157AADD"
    },
    {
      "block_id": 6,
      "ko": "상대와 비교해 본가의 위신과 병력이 부족합니다.",
      "literal_id": 0,
      "record_id": 1828,
      "source_sc_utf16le_sha256": "4ADA44A4E9D795784BA06DF641D42AF34FCA812293823ECDE4E52F4A08B931A9"
    },
    {
      "block_id": 6,
      "ko": "교전 중이거나 교전 직후인 세력과는 종속·신종 관계를 맺을 수 없습니다.",
      "literal_id": 0,
      "record_id": 1829,
      "source_sc_utf16le_sha256": "4B08BCC80D0AF29C0070923B1D1BE463451C67017D7A586E08AA77649D7B0893"
    },
    {
      "block_id": 6,
      "ko": "막부는 다른 가문의 휘하에 들어갈 수 없습니다.",
      "literal_id": 0,
      "record_id": 1830,
      "source_sc_utf16le_sha256": "1F2EBF1E5CE85CCAEABFE2A569A3BD6009458A599D25DDB58A0A570E1C8FDA91"
    },
    {
      "block_id": 6,
      "ko": "이미 상대와 주종 관계입니다.",
      "literal_id": 0,
      "record_id": 1831,
      "source_sc_utf16le_sha256": "00E7F1C46D271B93885F3C3C506DCFEC1E3AE70CF9729A6A7E1074CE58938A21"
    },
    {
      "block_id": 6,
      "ko": "본가가 다른 가문에 종속되어 있어 다른 가문에 신종할 수 없습니다.",
      "literal_id": 0,
      "record_id": 1832,
      "source_sc_utf16le_sha256": "C311B319BE70E8A12093B8B9651ABBDE33E737555018D9BCEA27C00FFD098277"
    },
    {
      "block_id": 6,
      "ko": "독립 상태가 아닌 세력에는 신종할 수 없습니다.",
      "literal_id": 0,
      "record_id": 1833,
      "source_sc_utf16le_sha256": "0FFF342CE4DD82C9354C9125D6DD69531A0889507ADEFF4AB3F82C16D4BEE54F"
    },
    {
      "block_id": 6,
      "ko": "다른 가문에 종속된 세력에는 신종할 수 없습니다.",
      "literal_id": 0,
      "record_id": 1834,
      "source_sc_utf16le_sha256": "3421D2FF3D64D4C7142B6A962FA31A9EEBB050A12FB06E3EB8C39016E67D6372"
    },
    {
      "block_id": 6,
      "ko": "본가 또는 종속 세력과 인접하지 않습니다.",
      "literal_id": 0,
      "record_id": 1835,
      "source_sc_utf16le_sha256": "AA319B119900B4AF47B2404B37B651FC89D4BAF7C39B7B432CAC0669EEEAC851"
    },
    {
      "block_id": 6,
      "ko": "상대가 본가의 신종을 거부하고 있습니다.",
      "literal_id": 0,
      "record_id": 1836,
      "source_sc_utf16le_sha256": "272EB4E9236F1E76A6322A21C8E0D39135BB5057FAD080607EEC163F519785DD"
    },
    {
      "block_id": 6,
      "ko": "상대는 본가에 아직 여력이 있다고 보아 신종을 의심하고 있습니다.",
      "literal_id": 0,
      "record_id": 1837,
      "source_sc_utf16le_sha256": "C1383DE7AE447074B9E043DE180C4FF4987BB2EE8717AF36D9CE76850EEDFE79"
    },
    {
      "block_id": 6,
      "ko": "본가의 규모로는 신종을 제안해도\n믿음을 얻을 수 없습니다.",
      "literal_id": 0,
      "record_id": 1838,
      "source_sc_utf16le_sha256": "701EB1F905240401635DA383A22445B3CBECA7BCE303AC94B78BF1E9D160206D"
    }
  ],
  "entry_count": 150,
  "overlay_id": "msggame_pk_system_messages_b06r1677_1838.v0.12",
  "resource": "MSG_PK/SC/msggame.bin",
  "schema": "nobu16.kr.msggame-literal-overlay.v1",
  "stock_sc": {
    "literal_slot_count": 25598,
    "packed_sha256": "BD7B33FCC7495B855B0828C7FE4E5F7ADB2DE656A9B12E20259750F94EE665D6",
    "packed_size": 529419,
    "raw_sha256": "1958B2B801D37186D478284EA0E29CA96D8DA2BC087D6BEB74A4139EF01C11CE",
    "raw_size": 1077200,
    "record_count": 21581
  }
}
